{"head": {"threshold": 0.0, "feathering": 0.25, "autozero": true, "tracker": "area", "saturation_correction": true}, "right": {"threshold": 0.0, "feathering": 0.25, "autozero": true, "tracker": "edge", "saturation_correction": true}, "n_edges_max": 1, "use_gui": true, "filenameBackground": "C:\\Users\\boc5244\\PycharmProjects\\Benifly\\image\\Benifly.png", "abdomen": {"threshold": 0.0, "feathering": 0.25, "autozero": true, "tracker": "tip", "saturation_correction": true}, "image_topic": "/camera/image_raw", "rc_background": 1000.0, "wingbeat_max": 220, "left": {"threshold": 0.0, "feathering": 0.25, "autozero": true, "tracker": "edge", "saturation_correction": true}, "wingbeat_min": 180, "aux": {"tracker": "intensity", "saturation_correction": true}, "out_fps": 60, "n_queue_images": 2, "gui": {"head": {"radius_outer": 51.73973328110612, "stabilize": false, "track": true, "subtract_bg": false, "angle_lo": -0.8167643911140212, "hinge": {"y": 104.0, "x": 258.0}, "angle_hi": 0.8167643911140212, "radius_inner": 41.19465984809196}, "right": {"radius_outer": 96.22374925616747, "stabilize": false, "track": true, "subtract_bg": false, "angle_lo": 0.31018992461512696, "hinge": {"y": 166.49561751035787, "x": 296.00192798979776}, "angle_hi": 2.0072133624728705, "radius_inner": 48.373546489791295}, "windows": false, "abdomen": {"radius_outer": 36.40054944640259, "stabilize": false, "track": false, "subtract_bg": false, "angle_lo": 1.8860110265456074, "hinge": {"y": 196.0, "x": 259.0}, "angle_hi": 4.369655659182342, "radius_inner": 23.40939982143925}, "symmetric": true, "aux": {"radius1": 30.0, "radius2": 29.0, "angle": 0.0, "center": {"y": 204.0, "x": 416.0}, "track": true, "subtract_bg": false}, "left": {"radius_outer": 96.22374925616747, "stabilize": false, "track": true, "subtract_bg": false, "angle_lo": -2.0072133624728705, "hinge": {"y": 167.3068831352962, "x": 221.36549049548108}, "angle_hi": -0.31018992461512696, "radius_inner": 48.373546489791295}, "axis": {"track": false, "pt2": {"y": 150, "x": 175}, "pt1": {"y": 50, "x": 175}}}, "scale_image": 1}